bareditor/__init__.py
bareditor/bareditor/__init__.py
bareditor/bareditor/config.py
bareditor/bareditor/doc.py
bareditor/bareditor/font.txt
bareditor/bareditor/main.py
bareditor/bareditor/rects.py
bareditor/bareditor/tools.py
bareditor/imgdata/__init__.py
bareditor/imgdata/barcode.ico
bareditor/imgdata/barcode.png
bareditor/imgdata/full.png
bareditor/imgdata/new.png
bareditor/imgdata/open.png
bareditor/imgdata/picture.png
bareditor/imgdata/printer.png
bareditor/imgdata/save.png
bareditor/imgdata/set.png
bareditor/imgdata/text.png
bareditor/imgdata/zoomin.png
bareditor/imgdata/zoomout.png
bareditor-0.16.dist-info/DESCRIPTION.rst
bareditor-0.16.dist-info/METADATA
bareditor-0.16.dist-info/RECORD
bareditor-0.16.dist-info/WHEEL
bareditor-0.16.dist-info/metadata.json
bareditor-0.16.dist-info/top_level.txt
