Metadata-Version: 2.0
Name: bareditor
Version: 0.16
Summary: interactive python image-processing plugin framework
Home-page: https://github.com/434625142/bareditor
Author: YXDragon
Author-email: yxdragon@imagepy.org
License: BSD 3-clause
Platform: UNKNOWN
Requires-Dist: wxpython
Requires-Dist: numba
Requires-Dist: pillow
